{"Иванов П.С.": {"ТН": "001", "Дата рождения": "17.10.1980", "Адрес": "Попова, 44", "Пол": "М", "Возраст": 42, "Телефон": "+876390444", "Должность": "Директор", "Оклад": 166650, "Отдел": "Администрация", "Стаж": "22", "email": "ips1980@gmail.com", "Дата приема": "14.02.2005"}, "Сергеева З.Л.": {"ТН": "002", "Дата рождения": "27.11.1983", "Адрес": "Самолетная, 18", "Пол": "Ж", "Возраст": 39, "Телефон": "+79121451402", "Должность": "Главный бухгалтер", "Оклад": 127765, "Отдел": "Бухгалтерия", "Стаж": "17", "email": "sergeeva@gmail.com", "Дата приема": "14.12.2005"}, "Григорьева Е.С.": {"ТН": "003", "Дата рождения": "27.07.1982", "Адрес": "Паркова, 65", "Пол": "Ж", "Возраст": 40, "Телефон": "+79435558888", "Должность": "Коммерческий директор", "Оклад": 140542, "Отдел": "Администрация", "Стаж": "22", "email": "es_grig@gmail.com", "Дата приема": "25.02.2015"}, "Тимофеев А.П.": {"ТН": "004", "Дата рождения": "21.10.1980", "Адрес": "Пушкинская, 39", "Пол": "М", "Возраст": 42, "Телефон": "89122225544", "Должность": "Зав.производством", "Оклад": 153318, "Отдел": "Администрация", "Стаж": "20", "email": "timofeev@gmail.com", "Дата приема": "14.04.2007"}}